sts/__init__.py
sts/base.py
sts/blockdevice.py
sts/dmpd.py
sts/fc.py
sts/isns.py
sts/loop.py
sts/multipath.py
sts/nvme.py
sts/pr.py
sts/qemu.py
sts/rdma.py
sts/scsi.py
sts/scsi_debug.py
sts/sg3_utils.py
sts/target.py
sts/udevadm.py
sts/vdo.py
sts/boom/__init__.py
sts/boom/base.py
sts/boom/entry.py
sts/boom/host.py
sts/boom/profile.py
sts/dm/__init__.py
sts/dm/base.py
sts/dm/cache.py
sts/dm/delay.py
sts/dm/error.py
sts/dm/flakey.py
sts/dm/linear.py
sts/dm/thin.py
sts/dm/vdo.py
sts/dm/zero.py
sts/fio/__init__.py
sts/fio/errors.py
sts/fio/fio.py
sts/fio/parameters.py
sts/fixtures/__init__.py
sts/fixtures/boom_fixtures.py
sts/fixtures/common_fixtures.py
sts/fixtures/dm_fixtures.py
sts/fixtures/fc_fixtures.py
sts/fixtures/iscsi_fixtures.py
sts/fixtures/lvm_fixtures.py
sts/fixtures/module_fixtures.py
sts/fixtures/multipath_fixtures.py
sts/fixtures/nvme_fixtures.py
sts/fixtures/rdma_fixtures.py
sts/fixtures/snapm_fixtures.py
sts/fixtures/stratis_fixtures.py
sts/fixtures/target_fixtures.py
sts/iscsi/__init__.py
sts/iscsi/config.py
sts/iscsi/device.py
sts/iscsi/iscsiadm.py
sts/iscsi/parameters.py
sts/iscsi/session.py
sts/lvm/__init__.py
sts/lvm/base.py
sts/lvm/logical_volume.py
sts/lvm/lvconf.py
sts/lvm/lvreport.py
sts/lvm/physical_volume.py
sts/lvm/volume_group.py
sts/network/__init__.py
sts/network/errors.py
sts/network/interface.py
sts/network/nm.py
sts/snapm/__init__.py
sts/snapm/base.py
sts/snapm/plugin.py
sts/snapm/snapset.py
sts/snapm/snapshot.py
sts/stratis/__init__.py
sts/stratis/base.py
sts/stratis/errors.py
sts/stratis/filesystem.py
sts/stratis/pool.py
sts/utils/__init__.py
sts/utils/cmdline.py
sts/utils/config.py
sts/utils/errors.py
sts/utils/files.py
sts/utils/host.py
sts/utils/modules.py
sts/utils/packages.py
sts/utils/processes.py
sts/utils/size.py
sts/utils/string_extras.py
sts/utils/syscheck.py
sts/utils/system.py
sts/utils/tmt.py
sts/utils/version.py
sts_libs-1.16.0.dist-info/METADATA
sts_libs-1.16.0.dist-info/WHEEL
sts_libs-1.16.0.dist-info/licenses/LICENSE
sts_libs-1.16.0.dist-info/RECORD
