Metadata-Version: 2.4
Name: sts-libs
Version: 1.16.0
Summary: Library for pytest-based Linux storage tests
Project-URL: Repository, https://gitlab.com/rh-kernel-stqe/sts/
Author-email: Martin Hoyer <mhoyer@redhat.com>, Filip Suba <fsuba@redhat.com>, Zhaojuan Guo <zguo@redhat.com>, Bruno Goncalves <bgoncalv@redhat.com>, Jakub Krysl <jkrysl@redhat.com>
Maintainer-email: Martin Hoyer <mhoyer@redhat.com>, Filip Suba <fsuba@redhat.com>, Zhaojuan Guo <zguo@redhat.com>
License-Expression: GPL-3.0-or-later
License-File: LICENSE
Classifier: Framework :: Hatch
Classifier: Intended Audience :: Developers
Classifier: License :: OSI Approved :: GNU General Public License v3 or later (GPLv3+)
Classifier: Operating System :: POSIX :: Linux
Classifier: Programming Language :: Python :: 3 :: Only
Classifier: Programming Language :: Python :: 3.9
Classifier: Topic :: Software Development :: Quality Assurance
Classifier: Topic :: Software Development :: Testing
Requires-Python: >=3.9
Requires-Dist: pytest-testinfra<11,>=10.1
Provides-Extra: docs
Requires-Dist: mkdocs-material~=9.5.44; extra == 'docs'
Requires-Dist: mkdocstrings-python~=1.12.0; extra == 'docs'
Requires-Dist: mkdocstrings~=0.27.0; extra == 'docs'
Requires-Dist: mkdocs~=1.6.1; extra == 'docs'
